main.py
tushare_mcp-0.1.6.dist-info/METADATA
tushare_mcp-0.1.6.dist-info/WHEEL
tushare_mcp-0.1.6.dist-info/entry_points.txt
tushare_mcp-0.1.6.dist-info/top_level.txt
tushare_mcp-0.1.6.dist-info/RECORD
