Metadata-Version: 2.4
Name: tushare-mcp
Version: 0.1.6
Summary: Add your description here
Requires-Python: >=3.12
Requires-Dist: argparse>=1.4.0
Requires-Dist: matplotlib>=3.10.1
Requires-Dist: mcp>=1.7.1
Requires-Dist: mplfinance>=0.12.10b0
Requires-Dist: pandas>=2.2.3
Requires-Dist: tushare>=1.4.21
